notebook_url/_version.py
notebook_url-0.2.11.data/data/share/jupyter/labextensions/notebook-url/install.json
notebook_url-0.2.11.dist-info/METADATA
notebook_url-0.2.11.dist-info/WHEEL
notebook_url-0.2.11.dist-info/licenses/LICENSE
notebook_url-0.2.11.dist-info/RECORD
