Metadata-Version: 2.3
Name: notebook_url
Version: 0.2.11
Dynamic: Keywords
Summary: Used to compress notebook content into a sharable url.
Project-URL: Homepage, https://github.com/github_username/notebook-url
Project-URL: Bug Tracker, https://github.com/github_username/notebook-url/issues
Project-URL: Repository, https://github.com/github_username/notebook-url.git
Author-email: Dylan Wootton <dwootton@mit.edu>
License: BSD 3-Clause License
License-File: LICENSE
Classifier: Framework :: Jupyter
Classifier: Framework :: Jupyter :: JupyterLab
Classifier: Framework :: Jupyter :: JupyterLab :: 4
Classifier: Framework :: Jupyter :: JupyterLab :: Extensions
Classifier: Framework :: Jupyter :: JupyterLab :: Extensions :: Prebuilt
Classifier: License :: OSI Approved :: BSD License
Classifier: Programming Language :: Python
Classifier: Programming Language :: Python :: 3
Classifier: Programming Language :: Python :: 3.8
Classifier: Programming Language :: Python :: 3.9
Classifier: Programming Language :: Python :: 3.10
Classifier: Programming Language :: Python :: 3.11
Requires-Python: >=3.8
